{
    "name": "toasty",
    "id": "toasty",
    "title": "Toasty",
    "description": "A simple module module to render toasty on crit fail.",
    "version": "0.0.5",
    "author": "The Tester",
    "scripts": [
      "scripts/index.js"
    ],
    "styles": [
      "styles/index.css"
    ],
    "minimumCoreVersion": "9",
    "url": "https://github.com/nurogenic/FoundryVTT",
    "manifest": "https://github.com/nurogenic/FoundryVTT/releases/download/0.0.5/module.json",
    "download": "https://github.com/nurogenic/FoundryVTT/releases/download/0.0.5/module.zip"
}